nettracer3d/__init__.py
nettracer3d/branch_stitcher.py
nettracer3d/cellpose_manager.py
nettracer3d/community_extractor.py
nettracer3d/endpoint_joiner.py
nettracer3d/excelotron.py
nettracer3d/filaments.py
nettracer3d/histos.py
nettracer3d/modularity.py
nettracer3d/morphology.py
nettracer3d/neighborhoods.py
nettracer3d/nettracer.py
nettracer3d/nettracer_gui.py
nettracer3d/network_analysis.py
nettracer3d/network_draw.py
nettracer3d/network_graph_widget.py
nettracer3d/node_draw.py
nettracer3d/painting.py
nettracer3d/proximity.py
nettracer3d/run.py
nettracer3d/segmenter.py
nettracer3d/segmenter_GPU.py
nettracer3d/simple_network.py
nettracer3d/smart_dilate.py
nettracer3d/stats.py
nettracer3d/tutorial.py
nettracer3d-1.3.6.dist-info/licenses/LICENSE
nettracer3d-1.3.6.dist-info/METADATA
nettracer3d-1.3.6.dist-info/WHEEL
nettracer3d-1.3.6.dist-info/entry_points.txt
nettracer3d-1.3.6.dist-info/top_level.txt
nettracer3d-1.3.6.dist-info/RECORD
