Metadata-Version: 2.4
Name: nettracer3d
Version: 1.3.6
Summary: Scripts for intializing and analyzing networks from segmentations of three dimensional images.
Author-email: Liam McLaughlin <liamm@wustl.edu>
Project-URL: Documentation, https://nettracer3d.readthedocs.io/en/latest/
Project-URL: Youtube_Tutorial, https://www.youtube.com/watch?v=_4uDy0mzG94&list=PLsrhxiimzKJMZ3_gTWkfrcAdJQQobUhj7
Project-URL: Downloadable_Version, https://doi.org/10.5281/zenodo.17873800
Classifier: Programming Language :: Python :: 3
Classifier: License :: Other/Proprietary License
Classifier: Operating System :: OS Independent
Requires-Python: >=3.7
License-File: LICENSE
Requires-Dist: numpy
Requires-Dist: scipy
Requires-Dist: scikit-image
Requires-Dist: Pillow
Requires-Dist: matplotlib
Requires-Dist: networkx
Requires-Dist: opencv-python-headless
Requires-Dist: openpyxl
Requires-Dist: pandas
Requires-Dist: tifffile
Requires-Dist: qtrangeslider
Requires-Dist: PyQt6
Requires-Dist: pyqtgraph
Requires-Dist: scikit-learn
Requires-Dist: setuptools
Requires-Dist: umap-learn
Provides-Extra: cuda11
Requires-Dist: cupy-cuda11x; extra == "cuda11"
Provides-Extra: cuda12
Requires-Dist: cupy-cuda12x; extra == "cuda12"
Provides-Extra: cupy
Requires-Dist: cupy; extra == "cupy"
Provides-Extra: cellpose
Requires-Dist: cellpose[GUI]; extra == "cellpose"
Provides-Extra: viz
Requires-Dist: napari; extra == "viz"
Provides-Extra: rec
Requires-Dist: napari; extra == "rec"
Requires-Dist: edt; extra == "rec"
Provides-Extra: edt
Requires-Dist: edt; extra == "edt"
Provides-Extra: all
Requires-Dist: cellpose[GUI]; extra == "all"
Requires-Dist: napari; extra == "all"
Requires-Dist: edt; extra == "all"
Dynamic: license-file
